<?xml version="1.0" encoding="UTF-8"?>
<objects serializationModel="Studio.02.02.00">
	<object class="AudioFile" id="{27348d88-815a-42c4-b668-19ccbc56763e}">
		<property name="assetPath">
			<value>Chime 6.wav</value>
		</property>
		<property name="isStreaming">
			<value>true</value>
		</property>
		<property name="frequencyInKHz">
			<value>48</value>
		</property>
		<property name="channelCount">
			<value>2</value>
		</property>
		<property name="length">
			<value>14</value>
		</property>
		<relationship name="masterAssetFolder">
			<destination>{2741e13b-fc55-41d9-8835-134a2244a42f}</destination>
		</relationship>
	</object>
</objects>
